zwave_js_server/__init__.py
zwave_js_server/__main__.py
zwave_js_server/client.py
zwave_js_server/dump.py
zwave_js_server/event.py
zwave_js_server/exceptions.py
zwave_js_server/firmware.py
zwave_js_server/py.typed
zwave_js_server/version.py
zwave_js_server/const/__init__.py
zwave_js_server/const/command_class/__init__.py
zwave_js_server/const/command_class/barrier_operator.py
zwave_js_server/const/command_class/basic.py
zwave_js_server/const/command_class/central_scene.py
zwave_js_server/const/command_class/color_switch.py
zwave_js_server/const/command_class/energy_production.py
zwave_js_server/const/command_class/entry_control.py
zwave_js_server/const/command_class/humidity_control.py
zwave_js_server/const/command_class/lock.py
zwave_js_server/const/command_class/meter.py
zwave_js_server/const/command_class/multilevel_sensor.py
zwave_js_server/const/command_class/multilevel_switch.py
zwave_js_server/const/command_class/notification.py
zwave_js_server/const/command_class/power_level.py
zwave_js_server/const/command_class/protection.py
zwave_js_server/const/command_class/scene_activation.py
zwave_js_server/const/command_class/sound_switch.py
zwave_js_server/const/command_class/thermostat.py
zwave_js_server/const/command_class/wake_up.py
zwave_js_server/const/command_class/window_covering.py
zwave_js_server/model/__init__.py
zwave_js_server/model/association.py
zwave_js_server/model/command_class.py
zwave_js_server/model/device_class.py
zwave_js_server/model/device_config.py
zwave_js_server/model/duration.py
zwave_js_server/model/endpoint.py
zwave_js_server/model/firmware.py
zwave_js_server/model/log_config.py
zwave_js_server/model/log_message.py
zwave_js_server/model/notification.py
zwave_js_server/model/statistics.py
zwave_js_server/model/utils.py
zwave_js_server/model/value.py
zwave_js_server/model/version.py
zwave_js_server/model/config_manager/__init__.py
zwave_js_server/model/controller/__init__.py
zwave_js_server/model/controller/data_model.py
zwave_js_server_python-0.68.0.dist-info/licenses/LICENSE
zwave_js_server_python-0.68.0.dist-info/METADATA
zwave_js_server_python-0.68.0.dist-info/WHEEL
zwave_js_server_python-0.68.0.dist-info/entry_points.txt
zwave_js_server_python-0.68.0.dist-info/top_level.txt
zwave_js_server_python-0.68.0.dist-info/RECORD
