Metadata-Version: 2.4
Name: zwave-js-server-python
Version: 0.68.0
Summary: Python wrapper for zwave-js-server
Author-email: Home Assistant Team <hello@home-assistant.io>
License-Expression: Apache-2.0
Project-URL: Source Code, https://github.com/home-assistant-libs/zwave-js-server-python
Project-URL: Bug Reports, https://github.com/home-assistant-libs/zwave-js-server-python/issues
Keywords: home,automation,zwave,zwave-js
Classifier: Development Status :: 4 - Beta
Classifier: Intended Audience :: Developers
Classifier: Natural Language :: English
Classifier: Programming Language :: Python :: 3
Classifier: Programming Language :: Python :: 3.12
Classifier: Programming Language :: Python :: 3.13
Classifier: Programming Language :: Python :: 3.14
Classifier: Topic :: Home Automation
Requires-Python: >=3.12
License-File: LICENSE
Requires-Dist: aiohttp>3
Requires-Dist: pydantic>=2.0.0
Dynamic: license-file
